comfy_ui_client/__init__.py
comfy_ui_client/client.py
comfy_ui_client/type.py
comfy_ui_client/util.py
tests/__init__.py
tests/test_client.py
comfy_ui_client-0.0.1.10.dist-info/LICENSE
comfy_ui_client-0.0.1.10.dist-info/METADATA
comfy_ui_client-0.0.1.10.dist-info/WHEEL
comfy_ui_client-0.0.1.10.dist-info/top_level.txt
comfy_ui_client-0.0.1.10.dist-info/RECORD
