Metadata-Version: 2.1
Name: comfy-ui-client
Version: 0.0.1.10
Summary: A simple WebSocket client for Comfy UI
Author: Gavin Bao
Author-email: xingce.bao@gmail.com
License: MIT
License-File: LICENSE
Requires-Dist: websocket-client
Requires-Dist: uuid
Requires-Dist: requests
Provides-Extra: dev
Requires-Dist: pytest >=6.0 ; extra == 'dev'
